velr/__init__.py
velr/_ffi.py
velr/driver.py
velr/jupyter.py
velr/jupyter_render.py
velr/nx.py
velr/sigma.py
velr/_vendor/__init__.py
velr/_vendor/libvelrc.so
velr-0.1.38.dist-info/METADATA
velr-0.1.38.dist-info/WHEEL
velr-0.1.38.dist-info/top_level.txt
velr-0.1.38.dist-info/RECORD
velr-0.1.38.dist-info/licenses/LICENSE
