Metadata-Version: 2.4
Name: velr
Version: 0.1.38
Summary: Python driver for Velr (bundles libvelr.* via _vendor/)
License-Expression: LicenseRef-Proprietary
Requires-Python: >=3.8
License-File: LICENSE
Requires-Dist: cffi>=1.15
Provides-Extra: pandas
Requires-Dist: pandas>=2; extra == "pandas"
Requires-Dist: pyarrow>=15; extra == "pandas"
Provides-Extra: polars
Requires-Dist: polars>=0.20; extra == "polars"
Requires-Dist: pyarrow>=15; extra == "polars"
Provides-Extra: nx
Requires-Dist: networkx>=3.2; extra == "nx"
Provides-Extra: all
Requires-Dist: pandas>=2; extra == "all"
Requires-Dist: polars>=0.20; extra == "all"
Requires-Dist: pyarrow>=15; extra == "all"
Requires-Dist: networkx>=3.2; extra == "all"
Provides-Extra: test
Requires-Dist: pytest>=7; extra == "test"
Requires-Dist: pytest-cov>=4; extra == "test"
Requires-Dist: networkx>=3.2; extra == "test"
Requires-Dist: pandas>=2; extra == "test"
Requires-Dist: polars>=0.20; extra == "test"
Requires-Dist: pyarrow>=15; extra == "test"
Dynamic: license-file
